setup.py
mess_server_proj_roma_june.egg-info/PKG-INFO
mess_server_proj_roma_june.egg-info/SOURCES.txt
mess_server_proj_roma_june.egg-info/dependency_links.txt
mess_server_proj_roma_june.egg-info/requires.txt
mess_server_proj_roma_june.egg-info/top_level.txt
server/__init__.py
server/server.py
server/common/__init__.py
server/common/common.py
server/common/decos.py
server/common/descryptors.py
server/common/errors.py
server/common/meta_classes.py
server/common/variables.py
server/logs/__init__.py
server/logs/client_log_config.py
server/logs/server_log_config.py
server/server/__init__.py
server/server/add_user.py
server/server/config_window.py
server/server/core.py
server/server/database.py
server/server/main_window.py
server/server/remove_user.py
server/server/stat_window.py