Metadata-Version: 1.0
Name: mess-server-proj-roma-june
Version: 0.0.2
Summary: mess_server_proj
Home-page: UNKNOWN
Author: Roman Khoroshev
Author-email: zizigi@yandex.ru
License: UNKNOWN
Platform: UNKNOWN
